isogeotodocx/__about__.py
isogeotodocx/__init__.py
isogeotodocx/isogeo2docx.py
isogeotodocx/utils/__init__.py
isogeotodocx/utils/formatter.py
isogeo_export_docx-1.1.3.dist-info/LICENSE
isogeo_export_docx-1.1.3.dist-info/METADATA
isogeo_export_docx-1.1.3.dist-info/WHEEL
isogeo_export_docx-1.1.3.dist-info/top_level.txt
isogeo_export_docx-1.1.3.dist-info/RECORD
