Metadata-Version: 2.1
Name: isogeo-export-docx
Version: 1.1.3
Summary: Export metadata from the Isogeo REST API into Microsoft Word documents (.docx).
Home-page: https://pypi.org/project/isogeo-export-docx/
Author: Isogeo
Author-email: dev@isogeo.com
License: LGPL3
Project-URL: Docs, https://isogeo-export-docx-py.readthedocs.io/
Project-URL: Bug Reports, https://pypi.org/project/isogeo-export-docx/issues/
Project-URL: Source, https://pypi.org/project/isogeo-export-docx/
Keywords: GIS metadata INSPIRE Isogeo API REST geographical data DOCX Word
Platform: UNKNOWN
Classifier: Intended Audience :: Developers
Classifier: Intended Audience :: Information Technology
Classifier: Programming Language :: Python :: 3
Classifier: Programming Language :: Python :: 3.6
Classifier: Programming Language :: Python :: 3.7
Classifier: Development Status :: 5 - Production/Stable
Classifier: License :: OSI Approved :: GNU General Public License v3 (GPLv3)
Classifier: Operating System :: OS Independent
Classifier: Topic :: Software Development :: Libraries :: Python Modules
Requires-Python: >=3.6, <4
Requires-Dist: isogeo-pysdk (<3.4,>=3.2)
Requires-Dist: docxtpl (==0.6.*)
Provides-Extra: dev
Requires-Dist: black ; extra == 'dev'
Requires-Dist: python-dotenv ; extra == 'dev'
Provides-Extra: test
Requires-Dist: pytest ; extra == 'test'
Requires-Dist: pytest-cov ; extra == 'test'
